mg_ml_helper/__init__.py
mg_ml_helper/check.py
mg_ml_helper/hp.py
mg_ml_helper-0.1.1.dist-info/METADATA
mg_ml_helper-0.1.1.dist-info/WHEEL
mg_ml_helper-0.1.1.dist-info/top_level.txt
mg_ml_helper-0.1.1.dist-info/RECORD
