Metadata-Version: 2.4
Name: mg_ml_helper
Version: 0.1.1
Author: Ganesh Gaikwad
Dynamic: author
Dynamic: description
Dynamic: description-content-type
